Workbook

Sheet One_Page_Dashboard
B1: OLIST E-COMMERCE DASHBOARD
B2: Sep 2016 - Oct 2018 | delivered orders | amounts in Brazilian Real (R$)
B4: TOTAL REVENUE | D4: DELIVERED ORDERS | F4: AVG ORDER VALUE | H4: AVG DELIVERY TIME | J4: LATE DELIVERY RATE | L4: AVG REVIEW SCORE
B5: ='01_KPI_Summary'!C4 -> 13221498 | D5: ='01_KPI_Summary'!A4 -> 96478 | F5: ='01_KPI_Summary'!E4 -> 137.04 | H5: ='01_KPI_Summary'!F4 -> 12.5 | J5: ='01_KPI_Summary'!H4 -> 6.77 | L5: ='01_KPI_Summary'!I4 -> 4.16
B6: Item sales, excluding freight | D6: =TEXT('01_KPI_Summary'!B4,"#,##0")&" unique customers" -> 93,358 unique customers | F6: Per delivered order | H6: ="Estimated: "&TEXT('01_KPI_Summary'!G4,"0.0")&" days" -> Estimated: 24.4 days | J6: Delivered after estimated date | L6: Average per order
B8: ="• DELIVERY HURTS REVIEWS: late orders average "&TEXT('13_Late_vs_OnTime'!C5,"0.00")&" stars vs "&TEXT('13_Late_vs_OnTime'!C4,"0.00")&" for on-time orders; "&TEXT('13_Late_vs_OnTime'!D5,"0")&"% of late orders get a negative review (1-2 stars) vs "&TEXT('13_Late_vs_OnTime'!D4,"0")&"%." -> • DELIVERY HURTS REVIEWS: late orders average 2.27 stars vs 4.29 for on-time orders; 62% of late orders get a negative review (1-2 stars) vs 9%.
B9: ="• CONCENTRATION: Sao Paulo (SP) generates "&TEXT('09_State_Performance'!D4/'01_KPI_Summary'!C4,"0%")&" of revenue; the top 3 categories make up "&TEXT(SUM('07_Category_Performance'!F4:F6),"0.0")&"% of sales." -> • CONCENTRATION: Sao Paulo (SP) generates 38% of revenue; the top 3 categories make up 25.9% of sales.
B10: ="• RETENTION GAP: only "&TEXT('17_Repeat_Customers'!C4,"0.0")&"% of customers ever bought a second time, so growth depends on acquiring new customers." -> • RETENTION GAP: only 3.0% of customers ever bought a second time, so growth depends on acquiring new customers.

Sheet Full_Dashboard
B1: OLIST E-COMMERCE PERFORMANCE DASHBOARD
B2: Brazilian marketplace | Sep 2016 to Oct 2018 | delivered orders only | amounts in Brazilian Real (R$) | Source: MySQL analysis of the Olist public dataset
B4: TOTAL REVENUE | D4: DELIVERED ORDERS | F4: AVG ORDER VALUE | H4: AVG DELIVERY TIME | J4: LATE DELIVERY RATE | L4: AVG REVIEW SCORE
B5: ='01_KPI_Summary'!C4 -> 13221498 | D5: ='01_KPI_Summary'!A4 -> 96478 | F5: ='01_KPI_Summary'!E4 -> 137.04 | H5: ='01_KPI_Summary'!F4 -> 12.5 | J5: ='01_KPI_Summary'!H4 -> 6.77 | L5: ='01_KPI_Summary'!I4 -> 4.16
B6: Item sales, excluding freight | D6: =TEXT('01_KPI_Summary'!B4,"#,##0")&" unique customers" -> 93,358 unique customers | F6: Per delivered order | H6: ="Estimated: "&TEXT('01_KPI_Summary'!G4,"0.0")&" days" -> Estimated: 24.4 days | J6: Delivered after estimated date | L6: Average per order
B8: KEY INSIGHTS
B9: ="1. GROWTH: Jan-Aug 2018 revenue was R$ "&TEXT(SUM('03_Monthly_Trend'!C19:C26)/1000000,"0.0")&"M vs R$ "&TEXT(SUM('03_Monthly_Trend'!C7:C14)/1000000,"0.0")&"M in Jan-Aug 2017, up "&TEXT(SUM('03_Monthly_Trend'!C19:C26)/SUM('03_Monthly_Trend'!C7:C14)-1,"0%")&"." -> 1. GROWTH: Jan-Aug 2018 revenue was R$ 7.2M vs R$ 3.0M in Jan-Aug 2017, up 141%.
B10: ="2. DELIVERY HURTS REVIEWS: late orders average "&TEXT('13_Late_vs_OnTime'!C5,"0.00")&" stars vs "&TEXT('13_Late_vs_OnTime'!C4,"0.00")&" for on-time orders; "&TEXT('13_Late_vs_OnTime'!D5,"0")&"% of late orders get a negative review (1-2 stars) vs "&TEXT('13_Late_vs_OnTime'!D4,"0")&"%." -> 2. DELIVERY HURTS REVIEWS: late orders average 2.27 stars vs 4.29 for on-time orders; 62% of late orders get a negative review (1-2 stars) vs 9%.
B11: ="3. LONGER DELAY, WORSE SCORE: orders arriving 8+ days late score "&TEXT('14_Delay_Buckets'!D9,"0.00")&" vs "&TEXT('14_Delay_Buckets'!D4,"0.00")&" for very early deliveries." -> 3. LONGER DELAY, WORSE SCORE: orders arriving 8+ days late score 1.70 vs 4.32 for very early deliveries.
B12: ="4. CONCENTRATION: Sao Paulo (SP) generates "&TEXT('09_State_Performance'!D4/'01_KPI_Summary'!C4,"0%")&" of revenue; the top 3 categories make up "&TEXT(SUM('07_Category_Performance'!F4:F6),"0.0")&"% of sales." -> 4. CONCENTRATION: Sao Paulo (SP) generates 38% of revenue; the top 3 categories make up 25.9% of sales.
B13: ="5. RETENTION GAP: only "&TEXT('17_Repeat_Customers'!C4,"0.0")&"% of customers ever bought a second time, so growth depends on acquiring new customers." -> 5. RETENTION GAP: only 3.0% of customers ever bought a second time, so growth depends on acquiring new customers.
B14: ="6. AT-RISK VALUE: "&TEXT('20_RFM_Segments'!B5,"#,##0")&" high-spend customers have not bought for ~"&TEXT('20_RFM_Segments'!D5,"0")&" days and hold "&TEXT('20_RFM_Segments'!H5,"0")&"% of revenue; "&TEXT('10_Payment_Types'!D4,"0")&"% of payment value is by credit card." -> 6. AT-RISK VALUE: 14,563 high-spend customers have not bought for ~394 days and hold 31% of revenue; 78% of payment value is by credit card.
B96: Definitions: Revenue = sum of item prices in delivered orders (freight excluded). Late = delivered on a date after the estimated delivery date. Customers are counted by customer_unique_id. See the About sheet.

Sheet Cohort_Heatmap
A1: Customer retention by first-purchase month (cohort)
A2: Each row is a cohort of customers who first bought in that month. Columns show the % of that cohort who bought again N months later (month 0 = first purchase = 100%). Darker = higher retention.
C3: Months since first purchase
A4: Cohort | B4: Cohort size | C4: 0 | D4: 1 | E4: 2 | F4: 3 | G4: 4 | H4: 5 | I4: 6 | J4: 7 | K4: 8 | L4: 9 | M4: 10 | N4: 11 | O4: 12
A5: 2017-01 | B5: =SUMPRODUCT(('19_Cohort_Retention'!$A$4:$A$222=$A5)*('19_Cohort_Retention'!$B$4:$B$222=0)*'19_Cohort_Retention'!$C$4:$C$222) -> 717 | C5: =IF(SUMPRODUCT(('19_Cohort_Retention'!$A$4:$A$222=$A5)*('19_Cohort_Retention'!$B$4:$B$222=C$4))=0,"",SUMPRODUCT(('19_Cohort_Retention'!$A$4:$A$222=$A5)*('19_Cohort_Retention'!$B$4:$B$222=C$4)*'19_Cohort_Retention'!$D$4:$D$222)) -> 100 | D5: =IF(SUMPRODUCT(('19_Cohort_Retention'!$A$4:$A$222=$A5)*('19_Cohort_Retention'!$B$4:$B$222=D$4))=0,"",SUMPRODUCT(('19_Cohort_Retention'!$A$4:$A$222=$A5)*('19_Cohort_Retention'!$B$4:$B$222=D$4)*'19_Cohort_Retention'!$D$4:$D$222)) -> 0.28 | E5: =IF(SUMPRODUCT(('19_Cohort_Retention'!$A$4:$A$222=$A5)*('19_Cohort_Retention'!$B$4:$B$222=E$4))=0,"",SUMPRODUCT(('19_Cohort_Retention'!$A$4:$A$222=$A5)*('19_Cohort_Retention'!$B$4:$B$222=E$4)*'19_Cohort_Retention'!$D$4:$D$222)) -> 0.28 | F5: =IF(SUMPRODUCT(('19_Cohort_Retention'!$A$4:$A$222=$A5)*('19_Cohort_Retention'!$B$4:$B$222=F$4))=0,"",SUMPRODUCT(('19_Cohort_Retention'!$A$4:$A$222=$A5)*('19_Cohort_Retention'!$B$4:$B$222=F$4)*'19_Cohort_Retention'!$D$4:$D$222)) -> 0.14 | G5: =IF(SUMPRODUCT(('19_Cohort_Retention'!$A$4:$A$222=$A5)*('19_Cohort_Retention'!$B$4:$B$222=G$4))=0,"",SUMPRODUCT(('19_Cohort_Retention'!$A$4:$A$222=$A5)*('19_Cohort_Retention'!$B$4:$B$222=G$4)*'19_Cohort_Retention'!$D$4:$D$222)) -> 0.42 | H5: =IF(SUMPRODUCT(('19_Cohort_Retention'!$A$4:$A$222=$A5)*('19_Cohort_Retention'!$B$4:$B$222=H$4))=0,"",SUMPRODUCT(('19_Cohort_Retention'!$A$4:$A$222=$A5)*('19_Cohort_Retention'!$B$4:$B$222=H$4)*'19_Cohort_Retention'!$D$4:$D$222)) -> 0.14 | I5: =IF(SUMPRODUCT(('19_Cohort_Retention'!$A$4:$A$222=$A5)*('19_Cohort_Retention'!$B$4:$B$222=I$4))=0,"",SUMPRODUCT(('19_Cohort_Retention'!$A$4:$A$222=$A5)*('19_Cohort_Retention'!$B$4:$B$222=I$4)*'19_Cohort_Retention'!$D$4:$D$222)) -> 0.42 | J5: =IF(SUMPRODUCT(('19_Cohort_Retention'!$A$4:$A$222=$A5)*('19_Cohort_Retention'!$B$4:$B$222=J$4))=0,"",SUMPRODUCT(('19_Cohort_Retention'!$A$4:$A$222=$A5)*('19_Cohort_Retention'!$B$4:$B$222=J$4)*'19_Cohort_Retention'!$D$4:$D$222)) -> 0.14 | ... O5: =IF(SUMPRODUCT(('19_Cohort_Retention'!$A$4:$A$222=$A5)*('19_Cohort_Retention'!$B$4:$B$222=O$4))=0,"",SUMPRODUCT(('19_Cohort_Retention'!$A$4:$A$222=$A5)*('19_Cohort_Retention'!$B$4:$B$222=O$4)*'19_Cohort_Retention'!$D$4:$D$222)) -> 0.7
A6: 2017-02 | B6: =SUMPRODUCT(('19_Cohort_Retention'!$A$4:$A$222=$A6)*('19_Cohort_Retention'!$B$4:$B$222=0)*'19_Cohort_Retention'!$C$4:$C$222) -> 1628 | C6: =IF(SUMPRODUCT(('19_Cohort_Retention'!$A$4:$A$222=$A6)*('19_Cohort_Retention'!$B$4:$B$222=C$4))=0,"",SUMPRODUCT(('19_Cohort_Retention'!$A$4:$A$222=$A6)*('19_Cohort_Retention'!$B$4:$B$222=C$4)*'19_Cohort_Retention'!$D$4:$D$222)) -> 100 | D6: =IF(SUMPRODUCT(('19_Cohort_Retention'!$A$4:$A$222=$A6)*('19_Cohort_Retention'!$B$4:$B$222=D$4))=0,"",SUMPRODUCT(('19_Cohort_Retention'!$A$4:$A$222=$A6)*('19_Cohort_Retention'!$B$4:$B$222=D$4)*'19_Cohort_Retention'!$D$4:$D$222)) -> 0.18 | E6: =IF(SUMPRODUCT(('19_Cohort_Retention'!$A$4:$A$222=$A6)*('19_Cohort_Retention'!$B$4:$B$222=E$4))=0,"",SUMPRODUCT(('19_Cohort_Retention'!$A$4:$A$222=$A6)*('19_Cohort_Retention'!$B$4:$B$222=E$4)*'19_Cohort_Retention'!$D$4:$D$222)) -> 0.31 | F6: =IF(SUMPRODUCT(('19_Cohort_Retention'!$A$4:$A$222=$A6)*('19_Cohort_Retention'!$B$4:$B$222=F$4))=0,"",SUMPRODUCT(('19_Cohort_Retention'!$A$4:$A$222=$A6)*('19_Cohort_Retention'!$B$4:$B$222=F$4)*'19_Cohort_Retention'!$D$4:$D$222)) -> 0.12 | G6: =IF(SUMPRODUCT(('19_Cohort_Retention'!$A$4:$A$222=$A6)*('19_Cohort_Retention'!$B$4:$B$222=G$4))=0,"",SUMPRODUCT(('19_Cohort_Retention'!$A$4:$A$222=$A6)*('19_Cohort_Retention'!$B$4:$B$222=G$4)*'19_Cohort_Retention'!$D$4:$D$222)) -> 0.43 | H6: =IF(SUMPRODUCT(('19_Cohort_Retention'!$A$4:$A$222=$A6)*('19_Cohort_Retention'!$B$4:$B$222=H$4))=0,"",SUMPRODUCT(('19_Cohort_Retention'!$A$4:$A$222=$A6)*('19_Cohort_Retention'!$B$4:$B$222=H$4)*'19_Cohort_Retention'!$D$4:$D$222)) -> 0.12 | I6: =IF(SUMPRODUCT(('19_Cohort_Retention'!$A$4:$A$222=$A6)*('19_Cohort_Retention'!$B$4:$B$222=I$4))=0,"",SUMPRODUCT(('19_Cohort_Retention'!$A$4:$A$222=$A6)*('19_Cohort_Retention'!$B$4:$B$222=I$4)*'19_Cohort_Retention'!$D$4:$D$222)) -> 0.25 | J6: =IF(SUMPRODUCT(('19_Cohort_Retention'!$A$4:$A$222=$A6)*('19_Cohort_Retention'!$B$4:$B$222=J$4))=0,"",SUMPRODUCT(('19_Cohort_Retention'!$A$4:$A$222=$A6)*('19_Cohort_Retention'!$B$4:$B$222=J$4)*'19_Cohort_Retention'!$D$4:$D$222)) -> 0.18 | ... O6: =IF(SUMPRODUCT(('19_Cohort_Retention'!$A$4:$A$222=$A6)*('19_Cohort_Retention'!$B$4:$B$222=O$4))=0,"",SUMPRODUCT(('19_Cohort_Retention'!$A$4:$A$222=$A6)*('19_Cohort_Retention'!$B$4:$B$222=O$4)*'19_Cohort_Retention'!$D$4:$D$222)) -> 0.12
A7: 2017-03 | B7: =SUMPRODUCT(('19_Cohort_Retention'!$A$4:$A$222=$A7)*('19_Cohort_Retention'!$B$4:$B$222=0)*'19_Cohort_Retention'!$C$4:$C$222) -> 2503 | C7: =IF(SUMPRODUCT(('19_Cohort_Retention'!$A$4:$A$222=$A7)*('19_Cohort_Retention'!$B$4:$B$222=C$4))=0,"",SUMPRODUCT(('19_Cohort_Retention'!$A$4:$A$222=$A7)*('19_Cohort_Retention'!$B$4:$B$222=C$4)*'19_Cohort_Retention'!$D$4:$D$222)) -> 100 | D7: =IF(SUMPRODUCT(('19_Cohort_Retention'!$A$4:$A$222=$A7)*('19_Cohort_Retention'!$B$4:$B$222=D$4))=0,"",SUMPRODUCT(('19_Cohort_Retention'!$A$4:$A$222=$A7)*('19_Cohort_Retention'!$B$4:$B$222=D$4)*'19_Cohort_Retention'!$D$4:$D$222)) -> 0.44 | E7: =IF(SUMPRODUCT(('19_Cohort_Retention'!$A$4:$A$222=$A7)*('19_Cohort_Retention'!$B$4:$B$222=E$4))=0,"",SUMPRODUCT(('19_Cohort_Retention'!$A$4:$A$222=$A7)*('19_Cohort_Retention'!$B$4:$B$222=E$4)*'19_Cohort_Retention'!$D$4:$D$222)) -> 0.36 | F7: =IF(SUMPRODUCT(('19_Cohort_Retention'!$A$4:$A$222=$A7)*('19_Cohort_Retention'!$B$4:$B$222=F$4))=0,"",SUMPRODUCT(('19_Cohort_Retention'!$A$4:$A$222=$A7)*('19_Cohort_Retention'!$B$4:$B$222=F$4)*'19_Cohort_Retention'!$D$4:$D$222)) -> 0.4 | G7: =IF(SUMPRODUCT(('19_Cohort_Retention'!$A$4:$A$222=$A7)*('19_Cohort_Retention'!$B$4:$B$222=G$4))=0,"",SUMPRODUCT(('19_Cohort_Retention'!$A$4:$A$222=$A7)*('19_Cohort_Retention'!$B$4:$B$222=G$4)*'19_Cohort_Retention'!$D$4:$D$222)) -> 0.36 | H7: =IF(SUMPRODUCT(('19_Cohort_Retention'!$A$4:$A$222=$A7)*('19_Cohort_Retention'!$B$4:$B$222=H$4))=0,"",SUMPRODUCT(('19_Cohort_Retention'!$A$4:$A$222=$A7)*('19_Cohort_Retention'!$B$4:$B$222=H$4)*'19_Cohort_Retention'!$D$4:$D$222)) -> 0.16 | I7: =IF(SUMPRODUCT(('19_Cohort_Retention'!$A$4:$A$222=$A7)*('19_Cohort_Retention'!$B$4:$B$222=I$4))=0,"",SUMPRODUCT(('19_Cohort_Retention'!$A$4:$A$222=$A7)*('19_Cohort_Retention'!$B$4:$B$222=I$4)*'19_Cohort_Retention'!$D$4:$D$222)) -> 0.16 | J7: =IF(SUMPRODUCT(('19_Cohort_Retention'!$A$4:$A$222=$A7)*('19_Cohort_Retention'!$B$4:$B$222=J$4))=0,"",SUMPRODUCT(('19_Cohort_Retention'!$A$4:$A$222=$A7)*('19_Cohort_Retention'!$B$4:$B$222=J$4)*'19_Cohort_Retention'!$D$4:$D$222)) -> 0.32 | ... O7: =IF(SUMPRODUCT(('19_Cohort_Retention'!$A$4:$A$222=$A7)*('19_Cohort_Retention'!$B$4:$B$222=O$4))=0,"",SUMPRODUCT(('19_Cohort_Retention'!$A$4:$A$222=$A7)*('19_Cohort_Retention'!$B$4:$B$222=O$4)*'19_Cohort_Retention'!$D$4:$D$222)) -> 0.2
A8: 2017-04 | B8: =SUMPRODUCT(('19_Cohort_Retention'!$A$4:$A$222=$A8)*('19_Cohort_Retention'!$B$4:$B$222=0)*'19_Cohort_Retention'!$C$4:$C$222) -> 2256 | C8: =IF(SUMPRODUCT(('19_Cohort_Retention'!$A$4:$A$222=$A8)*('19_Cohort_Retention'!$B$4:$B$222=C$4))=0,"",SUMPRODUCT(('19_Cohort_Retention'!$A$4:$A$222=$A8)*('19_Cohort_Retention'!$B$4:$B$222=C$4)*'19_Cohort_Retention'!$D$4:$D$222)) -> 100 | D8: =IF(SUMPRODUCT(('19_Cohort_Retention'!$A$4:$A$222=$A8)*('19_Cohort_Retention'!$B$4:$B$222=D$4))=0,"",SUMPRODUCT(('19_Cohort_Retention'!$A$4:$A$222=$A8)*('19_Cohort_Retention'!$B$4:$B$222=D$4)*'19_Cohort_Retention'!$D$4:$D$222)) -> 0.62 | E8: =IF(SUMPRODUCT(('19_Cohort_Retention'!$A$4:$A$222=$A8)*('19_Cohort_Retention'!$B$4:$B$222=E$4))=0,"",SUMPRODUCT(('19_Cohort_Retention'!$A$4:$A$222=$A8)*('19_Cohort_Retention'!$B$4:$B$222=E$4)*'19_Cohort_Retention'!$D$4:$D$222)) -> 0.22 | F8: =IF(SUMPRODUCT(('19_Cohort_Retention'!$A$4:$A$222=$A8)*('19_Cohort_Retention'!$B$4:$B$222=F$4))=0,"",SUMPRODUCT(('19_Cohort_Retention'!$A$4:$A$222=$A8)*('19_Cohort_Retention'!$B$4:$B$222=F$4)*'19_Cohort_Retention'!$D$4:$D$222)) -> 0.18 | G8: =IF(SUMPRODUCT(('19_Cohort_Retention'!$A$4:$A$222=$A8)*('19_Cohort_Retention'!$B$4:$B$222=G$4))=0,"",SUMPRODUCT(('19_Cohort_Retention'!$A$4:$A$222=$A8)*('19_Cohort_Retention'!$B$4:$B$222=G$4)*'19_Cohort_Retention'!$D$4:$D$222)) -> 0.27 | H8: =IF(SUMPRODUCT(('19_Cohort_Retention'!$A$4:$A$222=$A8)*('19_Cohort_Retention'!$B$4:$B$222=H$4))=0,"",SUMPRODUCT(('19_Cohort_Retention'!$A$4:$A$222=$A8)*('19_Cohort_Retention'!$B$4:$B$222=H$4)*'19_Cohort_Retention'!$D$4:$D$222)) -> 0.27 | I8: =IF(SUMPRODUCT(('19_Cohort_Retention'!$A$4:$A$222=$A8)*('19_Cohort_Retention'!$B$4:$B$222=I$4))=0,"",SUMPRODUCT(('19_Cohort_Retention'!$A$4:$A$222=$A8)*('19_Cohort_Retention'!$B$4:$B$222=I$4)*'19_Cohort_Retention'!$D$4:$D$222)) -> 0.35 | J8: =IF(SUMPRODUCT(('19_Cohort_Retention'!$A$4:$A$222=$A8)*('19_Cohort_Retention'!$B$4:$B$222=J$4))=0,"",SUMPRODUCT(('19_Cohort_Retention'!$A$4:$A$222=$A8)*('19_Cohort_Retention'!$B$4:$B$222=J$4)*'19_Cohort_Retention'!$D$4:$D$222)) -> 0.31 | ... O8: =IF(SUMPRODUCT(('19_Cohort_Retention'!$A$4:$A$222=$A8)*('19_Cohort_Retention'!$B$4:$B$222=O$4))=0,"",SUMPRODUCT(('19_Cohort_Retention'!$A$4:$A$222=$A8)*('19_Cohort_Retention'!$B$4:$B$222=O$4)*'19_Cohort_Retention'!$D$4:$D$222)) -> 0.04
A9: 2017-05 | B9: =SUMPRODUCT(('19_Cohort_Retention'!$A$4:$A$222=$A9)*('19_Cohort_Retention'!$B$4:$B$222=0)*'19_Cohort_Retention'!$C$4:$C$222) -> 3451 | C9: =IF(SUMPRODUCT(('19_Cohort_Retention'!$A$4:$A$222=$A9)*('19_Cohort_Retention'!$B$4:$B$222=C$4))=0,"",SUMPRODUCT(('19_Cohort_Retention'!$A$4:$A$222=$A9)*('19_Cohort_Retention'!$B$4:$B$222=C$4)*'19_Cohort_Retention'!$D$4:$D$222)) -> 100 | D9: =IF(SUMPRODUCT(('19_Cohort_Retention'!$A$4:$A$222=$A9)*('19_Cohort_Retention'!$B$4:$B$222=D$4))=0,"",SUMPRODUCT(('19_Cohort_Retention'!$A$4:$A$222=$A9)*('19_Cohort_Retention'!$B$4:$B$222=D$4)*'19_Cohort_Retention'!$D$4:$D$222)) -> 0.46 | E9: =IF(SUMPRODUCT(('19_Cohort_Retention'!$A$4:$A$222=$A9)*('19_Cohort_Retention'!$B$4:$B$222=E$4))=0,"",SUMPRODUCT(('19_Cohort_Retention'!$A$4:$A$222=$A9)*('19_Cohort_Retention'!$B$4:$B$222=E$4)*'19_Cohort_Retention'!$D$4:$D$222)) -> 0.46 | F9: =IF(SUMPRODUCT(('19_Cohort_Retention'!$A$4:$A$222=$A9)*('19_Cohort_Retention'!$B$4:$B$222=F$4))=0,"",SUMPRODUCT(('19_Cohort_Retention'!$A$4:$A$222=$A9)*('19_Cohort_Retention'!$B$4:$B$222=F$4)*'19_Cohort_Retention'!$D$4:$D$222)) -> 0.29 | G9: =IF(SUMPRODUCT(('19_Cohort_Retention'!$A$4:$A$222=$A9)*('19_Cohort_Retention'!$B$4:$B$222=G$4))=0,"",SUMPRODUCT(('19_Cohort_Retention'!$A$4:$A$222=$A9)*('19_Cohort_Retention'!$B$4:$B$222=G$4)*'19_Cohort_Retention'!$D$4:$D$222)) -> 0.29 | H9: =IF(SUMPRODUCT(('19_Cohort_Retention'!$A$4:$A$222=$A9)*('19_Cohort_Retention'!$B$4:$B$222=H$4))=0,"",SUMPRODUCT(('19_Cohort_Retention'!$A$4:$A$222=$A9)*('19_Cohort_Retention'!$B$4:$B$222=H$4)*'19_Cohort_Retention'!$D$4:$D$222)) -> 0.32 | I9: =IF(SUMPRODUCT(('19_Cohort_Retention'!$A$4:$A$222=$A9)*('19_Cohort_Retention'!$B$4:$B$222=I$4))=0,"",SUMPRODUCT(('19_Cohort_Retention'!$A$4:$A$222=$A9)*('19_Cohort_Retention'!$B$4:$B$222=I$4)*'19_Cohort_Retention'!$D$4:$D$222)) -> 0.41 | J9: =IF(SUMPRODUCT(('19_Cohort_Retention'!$A$4:$A$222=$A9)*('19_Cohort_Retention'!$B$4:$B$222=J$4))=0,"",SUMPRODUCT(('19_Cohort_Retention'!$A$4:$A$222=$A9)*('19_Cohort_Retention'!$B$4:$B$222=J$4)*'19_Cohort_Retention'!$D$4:$D$222)) -> 0.14 | ... O9: =IF(SUMPRODUCT(('19_Cohort_Retention'!$A$4:$A$222=$A9)*('19_Cohort_Retention'!$B$4:$B$222=O$4))=0,"",SUMPRODUCT(('19_Cohort_Retention'!$A$4:$A$222=$A9)*('19_Cohort_Retention'!$B$4:$B$222=O$4)*'19_Cohort_Retention'!$D$4:$D$222)) -> 0.23
A10: 2017-06 | B10: =SUMPRODUCT(('19_Cohort_Retention'!$A$4:$A$222=$A10)*('19_Cohort_Retention'!$B$4:$B$222=0)*'19_Cohort_Retention'!$C$4:$C$222) -> 3037 | C10: =IF(SUMPRODUCT(('19_Cohort_Retention'!$A$4:$A$222=$A10)*('19_Cohort_Retention'!$B$4:$B$222=C$4))=0,"",SUMPRODUCT(('19_Cohort_Retention'!$A$4:$A$222=$A10)*('19_Cohort_Retention'!$B$4:$B$222=C$4)*'19_Cohort_Retention'!$D$4:$D$222)) -> 100 | D10: =IF(SUMPRODUCT(('19_Cohort_Retention'!$A$4:$A$222=$A10)*('19_Cohort_Retention'!$B$4:$B$222=D$4))=0,"",SUMPRODUCT(('19_Cohort_Retention'!$A$4:$A$222=$A10)*('19_Cohort_Retention'!$B$4:$B$222=D$4)*'19_Cohort_Retention'!$D$4:$D$222)) -> 0.49 | E10: =IF(SUMPRODUCT(('19_Cohort_Retention'!$A$4:$A$222=$A10)*('19_Cohort_Retention'!$B$4:$B$222=E$4))=0,"",SUMPRODUCT(('19_Cohort_Retention'!$A$4:$A$222=$A10)*('19_Cohort_Retention'!$B$4:$B$222=E$4)*'19_Cohort_Retention'!$D$4:$D$222)) -> 0.4 | F10: =IF(SUMPRODUCT(('19_Cohort_Retention'!$A$4:$A$222=$A10)*('19_Cohort_Retention'!$B$4:$B$222=F$4))=0,"",SUMPRODUCT(('19_Cohort_Retention'!$A$4:$A$222=$A10)*('19_Cohort_Retention'!$B$4:$B$222=F$4)*'19_Cohort_Retention'!$D$4:$D$222)) -> 0.43 | G10: =IF(SUMPRODUCT(('19_Cohort_Retention'!$A$4:$A$222=$A10)*('19_Cohort_Retention'!$B$4:$B$222=G$4))=0,"",SUMPRODUCT(('19_Cohort_Retention'!$A$4:$A$222=$A10)*('19_Cohort_Retention'!$B$4:$B$222=G$4)*'19_Cohort_Retention'!$D$4:$D$222)) -> 0.3 | H10: =IF(SUMPRODUCT(('19_Cohort_Retention'!$A$4:$A$222=$A10)*('19_Cohort_Retention'!$B$4:$B$222=H$4))=0,"",SUMPRODUCT(('19_Cohort_Retention'!$A$4:$A$222=$A10)*('19_Cohort_Retention'!$B$4:$B$222=H$4)*'19_Cohort_Retention'!$D$4:$D$222)) -> 0.4 | I10: =IF(SUMPRODUCT(('19_Cohort_Retention'!$A$4:$A$222=$A10)*('19_Cohort_Retention'!$B$4:$B$222=I$4))=0,"",SUMPRODUCT(('19_Cohort_Retention'!$A$4:$A$222=$A10)*('19_Cohort_Retention'!$B$4:$B$222=I$4)*'19_Cohort_Retention'!$D$4:$D$222)) -> 0.36 | J10: =IF(SUMPRODUCT(('19_Cohort_Retention'!$A$4:$A$222=$A10)*('19_Cohort_Retention'!$B$4:$B$222=J$4))=0,"",SUMPRODUCT(('19_Cohort_Retention'!$A$4:$A$222=$A10)*('19_Cohort_Retention'!$B$4:$B$222=J$4)*'19_Cohort_Retention'!$D$4:$D$222)) -> 0.23 | ... O10: =IF(SUMPRODUCT(('19_Cohort_Retention'!$A$4:$A$222=$A10)*('19_Cohort_Retention'!$B$4:$B$222=O$4))=0,"",SUMPRODUCT(('19_Cohort_Retention'!$A$4:$A$222=$A10)*('19_Cohort_Retention'!$B$4:$B$222=O$4)*'19_Cohort_Retention'!$D$4:$D$222)) -> 0.16
A11: 2017-07 | B11: =SUMPRODUCT(('19_Cohort_Retention'!$A$4:$A$222=$A11)*('19_Cohort_Retention'!$B$4:$B$222=0)*'19_Cohort_Retention'!$C$4:$C$222) -> 3752 | C11: =IF(SUMPRODUCT(('19_Cohort_Retention'!$A$4:$A$222=$A11)*('19_Cohort_Retention'!$B$4:$B$222=C$4))=0,"",SUMPRODUCT(('19_Cohort_Retention'!$A$4:$A$222=$A11)*('19_Cohort_Retention'!$B$4:$B$222=C$4)*'19_Cohort_Retention'!$D$4:$D$222)) -> 100 | D11: =IF(SUMPRODUCT(('19_Cohort_Retention'!$A$4:$A$222=$A11)*('19_Cohort_Retention'!$B$4:$B$222=D$4))=0,"",SUMPRODUCT(('19_Cohort_Retention'!$A$4:$A$222=$A11)*('19_Cohort_Retention'!$B$4:$B$222=D$4)*'19_Cohort_Retention'!$D$4:$D$222)) -> 0.53 | E11: =IF(SUMPRODUCT(('19_Cohort_Retention'!$A$4:$A$222=$A11)*('19_Cohort_Retention'!$B$4:$B$222=E$4))=0,"",SUMPRODUCT(('19_Cohort_Retention'!$A$4:$A$222=$A11)*('19_Cohort_Retention'!$B$4:$B$222=E$4)*'19_Cohort_Retention'!$D$4:$D$222)) -> 0.35 | F11: =IF(SUMPRODUCT(('19_Cohort_Retention'!$A$4:$A$222=$A11)*('19_Cohort_Retention'!$B$4:$B$222=F$4))=0,"",SUMPRODUCT(('19_Cohort_Retention'!$A$4:$A$222=$A11)*('19_Cohort_Retention'!$B$4:$B$222=F$4)*'19_Cohort_Retention'!$D$4:$D$222)) -> 0.24 | G11: =IF(SUMPRODUCT(('19_Cohort_Retention'!$A$4:$A$222=$A11)*('19_Cohort_Retention'!$B$4:$B$222=G$4))=0,"",SUMPRODUCT(('19_Cohort_Retention'!$A$4:$A$222=$A11)*('19_Cohort_Retention'!$B$4:$B$222=G$4)*'19_Cohort_Retention'!$D$4:$D$222)) -> 0.29 | H11: =IF(SUMPRODUCT(('19_Cohort_Retention'!$A$4:$A$222=$A11)*('19_Cohort_Retention'!$B$4:$B$222=H$4))=0,"",SUMPRODUCT(('19_Cohort_Retention'!$A$4:$A$222=$A11)*('19_Cohort_Retention'!$B$4:$B$222=H$4)*'19_Cohort_Retention'!$D$4:$D$222)) -> 0.21 | I11: =IF(SUMPRODUCT(('19_Cohort_Retention'!$A$4:$A$222=$A11)*('19_Cohort_Retention'!$B$4:$B$222=I$4))=0,"",SUMPRODUCT(('19_Cohort_Retention'!$A$4:$A$222=$A11)*('19_Cohort_Retention'!$B$4:$B$222=I$4)*'19_Cohort_Retention'!$D$4:$D$222)) -> 0.32 | J11: =IF(SUMPRODUCT(('19_Cohort_Retention'!$A$4:$A$222=$A11)*('19_Cohort_Retention'!$B$4:$B$222=J$4))=0,"",SUMPRODUCT(('19_Cohort_Retention'!$A$4:$A$222=$A11)*('19_Cohort_Retention'!$B$4:$B$222=J$4)*'19_Cohort_Retention'!$D$4:$D$222)) -> 0.11 | ... O11: =IF(SUMPRODUCT(('19_Cohort_Retention'!$A$4:$A$222=$A11)*('19_Cohort_Retention'!$B$4:$B$222=O$4))=0,"",SUMPRODUCT(('19_Cohort_Retention'!$A$4:$A$222=$A11)*('19_Cohort_Retention'!$B$4:$B$222=O$4)*'19_Cohort_Retention'!$D$4:$D$222)) -> 0.13
A12: 2017-08 | B12: =SUMPRODUCT(('19_Cohort_Retention'!$A$4:$A$222=$A12)*('19_Cohort_Retention'!$B$4:$B$222=0)*'19_Cohort_Retention'!$C$4:$C$222) -> 4057 | C12: =IF(SUMPRODUCT(('19_Cohort_Retention'!$A$4:$A$222=$A12)*('19_Cohort_Retention'!$B$4:$B$222=C$4))=0,"",SUMPRODUCT(('19_Cohort_Retention'!$A$4:$A$222=$A12)*('19_Cohort_Retention'!$B$4:$B$222=C$4)*'19_Cohort_Retention'!$D$4:$D$222)) -> 100 | D12: =IF(SUMPRODUCT(('19_Cohort_Retention'!$A$4:$A$222=$A12)*('19_Cohort_Retention'!$B$4:$B$222=D$4))=0,"",SUMPRODUCT(('19_Cohort_Retention'!$A$4:$A$222=$A12)*('19_Cohort_Retention'!$B$4:$B$222=D$4)*'19_Cohort_Retention'!$D$4:$D$222)) -> 0.69 | E12: =IF(SUMPRODUCT(('19_Cohort_Retention'!$A$4:$A$222=$A12)*('19_Cohort_Retention'!$B$4:$B$222=E$4))=0,"",SUMPRODUCT(('19_Cohort_Retention'!$A$4:$A$222=$A12)*('19_Cohort_Retention'!$B$4:$B$222=E$4)*'19_Cohort_Retention'!$D$4:$D$222)) -> 0.35 | F12: =IF(SUMPRODUCT(('19_Cohort_Retention'!$A$4:$A$222=$A12)*('19_Cohort_Retention'!$B$4:$B$222=F$4))=0,"",SUMPRODUCT(('19_Cohort_Retention'!$A$4:$A$222=$A12)*('19_Cohort_Retention'!$B$4:$B$222=F$4)*'19_Cohort_Retention'!$D$4:$D$222)) -> 0.27 | G12: =IF(SUMPRODUCT(('19_Cohort_Retention'!$A$4:$A$222=$A12)*('19_Cohort_Retention'!$B$4:$B$222=G$4))=0,"",SUMPRODUCT(('19_Cohort_Retention'!$A$4:$A$222=$A12)*('19_Cohort_Retention'!$B$4:$B$222=G$4)*'19_Cohort_Retention'!$D$4:$D$222)) -> 0.35 | H12: =IF(SUMPRODUCT(('19_Cohort_Retention'!$A$4:$A$222=$A12)*('19_Cohort_Retention'!$B$4:$B$222=H$4))=0,"",SUMPRODUCT(('19_Cohort_Retention'!$A$4:$A$222=$A12)*('19_Cohort_Retention'!$B$4:$B$222=H$4)*'19_Cohort_Retention'!$D$4:$D$222)) -> 0.52 | I12: =IF(SUMPRODUCT(('19_Cohort_Retention'!$A$4:$A$222=$A12)*('19_Cohort_Retention'!$B$4:$B$222=I$4))=0,"",SUMPRODUCT(('19_Cohort_Retention'!$A$4:$A$222=$A12)*('19_Cohort_Retention'!$B$4:$B$222=I$4)*'19_Cohort_Retention'!$D$4:$D$222)) -> 0.3 | J12: =IF(SUMPRODUCT(('19_Cohort_Retention'!$A$4:$A$222=$A12)*('19_Cohort_Retention'!$B$4:$B$222=J$4))=0,"",SUMPRODUCT(('19_Cohort_Retention'!$A$4:$A$222=$A12)*('19_Cohort_Retention'!$B$4:$B$222=J$4)*'19_Cohort_Retention'!$D$4:$D$222)) -> 0.27 | ... O12: =IF(SUMPRODUCT(('19_Cohort_Retention'!$A$4:$A$222=$A12)*('19_Cohort_Retention'!$B$4:$B$222=O$4))=0,"",SUMPRODUCT(('19_Cohort_Retention'!$A$4:$A$222=$A12)*('19_Cohort_Retention'!$B$4:$B$222=O$4)*'19_Cohort_Retention'!$D$4:$D$222)) -> 0.12
A13: 2017-09 | B13: =SUMPRODUCT(('19_Cohort_Retention'!$A$4:$A$222=$A13)*('19_Cohort_Retention'!$B$4:$B$222=0)*'19_Cohort_Retention'!$C$4:$C$222) -> 4004 | C13: =IF(SUMPRODUCT(('19_Cohort_Retention'!$A$4:$A$222=$A13)*('19_Cohort_Retention'!$B$4:$B$222=C$4))=0,"",SUMPRODUCT(('19_Cohort_Retention'!$A$4:$A$222=$A13)*('19_Cohort_Retention'!$B$4:$B$222=C$4)*'19_Cohort_Retention'!$D$4:$D$222)) -> 100 | D13: =IF(SUMPRODUCT(('19_Cohort_Retention'!$A$4:$A$222=$A13)*('19_Cohort_Retention'!$B$4:$B$222=D$4))=0,"",SUMPRODUCT(('19_Cohort_Retention'!$A$4:$A$222=$A13)*('19_Cohort_Retention'!$B$4:$B$222=D$4)*'19_Cohort_Retention'!$D$4:$D$222)) -> 0.7 | E13: =IF(SUMPRODUCT(('19_Cohort_Retention'!$A$4:$A$222=$A13)*('19_Cohort_Retention'!$B$4:$B$222=E$4))=0,"",SUMPRODUCT(('19_Cohort_Retention'!$A$4:$A$222=$A13)*('19_Cohort_Retention'!$B$4:$B$222=E$4)*'19_Cohort_Retention'!$D$4:$D$222)) -> 0.55 | F13: =IF(SUMPRODUCT(('19_Cohort_Retention'!$A$4:$A$222=$A13)*('19_Cohort_Retention'!$B$4:$B$222=F$4))=0,"",SUMPRODUCT(('19_Cohort_Retention'!$A$4:$A$222=$A13)*('19_Cohort_Retention'!$B$4:$B$222=F$4)*'19_Cohort_Retention'!$D$4:$D$222)) -> 0.27 | G13: =IF(SUMPRODUCT(('19_Cohort_Retention'!$A$4:$A$222=$A13)*('19_Cohort_Retention'!$B$4:$B$222=G$4))=0,"",SUMPRODUCT(('19_Cohort_Retention'!$A$4:$A$222=$A13)*('19_Cohort_Retention'!$B$4:$B$222=G$4)*'19_Cohort_Retention'!$D$4:$D$222)) -> 0.45 | H13: =IF(SUMPRODUCT(('19_Cohort_Retention'!$A$4:$A$222=$A13)*('19_Cohort_Retention'!$B$4:$B$222=H$4))=0,"",SUMPRODUCT(('19_Cohort_Retention'!$A$4:$A$222=$A13)*('19_Cohort_Retention'!$B$4:$B$222=H$4)*'19_Cohort_Retention'!$D$4:$D$222)) -> 0.22 | I13: =IF(SUMPRODUCT(('19_Cohort_Retention'!$A$4:$A$222=$A13)*('19_Cohort_Retention'!$B$4:$B$222=I$4))=0,"",SUMPRODUCT(('19_Cohort_Retention'!$A$4:$A$222=$A13)*('19_Cohort_Retention'!$B$4:$B$222=I$4)*'19_Cohort_Retention'!$D$4:$D$222)) -> 0.22 | J13: =IF(SUMPRODUCT(('19_Cohort_Retention'!$A$4:$A$222=$A13)*('19_Cohort_Retention'!$B$4:$B$222=J$4))=0,"",SUMPRODUCT(('19_Cohort_Retention'!$A$4:$A$222=$A13)*('19_Cohort_Retention'!$B$4:$B$222=J$4)*'19_Cohort_Retention'!$D$4:$D$222)) -> 0.25 | ... O13: =IF(SUMPRODUCT(('19_Cohort_Retention'!$A$4:$A$222=$A13)*('19_Cohort_Retention'!$B$4:$B$222=O$4))=0,"",SUMPRODUCT(('19_Cohort_Retention'!$A$4:$A$222=$A13)*('19_Cohort_Retention'!$B$4:$B$222=O$4)*'19_Cohort_Retention'!$D$4:$D$222))
A14: 2017-10 | B14: =SUMPRODUCT(('19_Cohort_Retention'!$A$4:$A$222=$A14)*('19_Cohort_Retention'!$B$4:$B$222=0)*'19_Cohort_Retention'!$C$4:$C$222) -> 4328 | C14: =IF(SUMPRODUCT(('19_Cohort_Retention'!$A$4:$A$222=$A14)*('19_Cohort_Retention'!$B$4:$B$222=C$4))=0,"",SUMPRODUCT(('19_Cohort_Retention'!$A$4:$A$222=$A14)*('19_Cohort_Retention'!$B$4:$B$222=C$4)*'19_Cohort_Retention'!$D$4:$D$222)) -> 100 | D14: =IF(SUMPRODUCT(('19_Cohort_Retention'!$A$4:$A$222=$A14)*('19_Cohort_Retention'!$B$4:$B$222=D$4))=0,"",SUMPRODUCT(('19_Cohort_Retention'!$A$4:$A$222=$A14)*('19_Cohort_Retention'!$B$4:$B$222=D$4)*'19_Cohort_Retention'!$D$4:$D$222)) -> 0.72 | E14: =IF(SUMPRODUCT(('19_Cohort_Retention'!$A$4:$A$222=$A14)*('19_Cohort_Retention'!$B$4:$B$222=E$4))=0,"",SUMPRODUCT(('19_Cohort_Retention'!$A$4:$A$222=$A14)*('19_Cohort_Retention'!$B$4:$B$222=E$4)*'19_Cohort_Retention'!$D$4:$D$222)) -> 0.25 | F14: =IF(SUMPRODUCT(('19_Cohort_Retention'!$A$4:$A$222=$A14)*('19_Cohort_Retention'!$B$4:$B$222=F$4))=0,"",SUMPRODUCT(('19_Cohort_Retention'!$A$4:$A$222=$A14)*('19_Cohort_Retention'!$B$4:$B$222=F$4)*'19_Cohort_Retention'!$D$4:$D$222)) -> 0.09 | G14: =IF(SUMPRODUCT(('19_Cohort_Retention'!$A$4:$A$222=$A14)*('19_Cohort_Retention'!$B$4:$B$222=G$4))=0,"",SUMPRODUCT(('19_Cohort_Retention'!$A$4:$A$222=$A14)*('19_Cohort_Retention'!$B$4:$B$222=G$4)*'19_Cohort_Retention'!$D$4:$D$222)) -> 0.23 | H14: =IF(SUMPRODUCT(('19_Cohort_Retention'!$A$4:$A$222=$A14)*('19_Cohort_Retention'!$B$4:$B$222=H$4))=0,"",SUMPRODUCT(('19_Cohort_Retention'!$A$4:$A$222=$A14)*('19_Cohort_Retention'!$B$4:$B$222=H$4)*'19_Cohort_Retention'!$D$4:$D$222)) -> 0.21 | I14: =IF(SUMPRODUCT(('19_Cohort_Retention'!$A$4:$A$222=$A14)*('19_Cohort_Retention'!$B$4:$B$222=I$4))=0,"",SUMPRODUCT(('19_Cohort_Retention'!$A$4:$A$222=$A14)*('19_Cohort_Retention'!$B$4:$B$222=I$4)*'19_Cohort_Retention'!$D$4:$D$222)) -> 0.21 | J14: =IF(SUMPRODUCT(('19_Cohort_Retention'!$A$4:$A$222=$A14)*('19_Cohort_Retention'!$B$4:$B$222=J$4))=0,"",SUMPRODUCT(('19_Cohort_Retention'!$A$4:$A$222=$A14)*('19_Cohort_Retention'!$B$4:$B$222=J$4)*'19_Cohort_Retention'!$D$4:$D$222)) -> 0.37 | ... O14: =IF(SUMPRODUCT(('19_Cohort_Retention'!$A$4:$A$222=$A14)*('19_Cohort_Retention'!$B$4:$B$222=O$4))=0,"",SUMPRODUCT(('19_Cohort_Retention'!$A$4:$A$222=$A14)*('19_Cohort_Retention'!$B$4:$B$222=O$4)*'19_Cohort_Retention'!$D$4:$D$222))
A15: 2017-11 | B15: =SUMPRODUCT(('19_Cohort_Retention'!$A$4:$A$222=$A15)*('19_Cohort_Retention'!$B$4:$B$222=0)*'19_Cohort_Retention'!$C$4:$C$222) -> 7060 | C15: =IF(SUMPRODUCT(('19_Cohort_Retention'!$A$4:$A$222=$A15)*('19_Cohort_Retention'!$B$4:$B$222=C$4))=0,"",SUMPRODUCT(('19_Cohort_Retention'!$A$4:$A$222=$A15)*('19_Cohort_Retention'!$B$4:$B$222=C$4)*'19_Cohort_Retention'!$D$4:$D$222)) -> 100 | D15: =IF(SUMPRODUCT(('19_Cohort_Retention'!$A$4:$A$222=$A15)*('19_Cohort_Retention'!$B$4:$B$222=D$4))=0,"",SUMPRODUCT(('19_Cohort_Retention'!$A$4:$A$222=$A15)*('19_Cohort_Retention'!$B$4:$B$222=D$4)*'19_Cohort_Retention'!$D$4:$D$222)) -> 0.57 | E15: =IF(SUMPRODUCT(('19_Cohort_Retention'!$A$4:$A$222=$A15)*('19_Cohort_Retention'!$B$4:$B$222=E$4))=0,"",SUMPRODUCT(('19_Cohort_Retention'!$A$4:$A$222=$A15)*('19_Cohort_Retention'!$B$4:$B$222=E$4)*'19_Cohort_Retention'!$D$4:$D$222)) -> 0.37 | F15: =IF(SUMPRODUCT(('19_Cohort_Retention'!$A$4:$A$222=$A15)*('19_Cohort_Retention'!$B$4:$B$222=F$4))=0,"",SUMPRODUCT(('19_Cohort_Retention'!$A$4:$A$222=$A15)*('19_Cohort_Retention'!$B$4:$B$222=F$4)*'19_Cohort_Retention'!$D$4:$D$222)) -> 0.17 | G15: =IF(SUMPRODUCT(('19_Cohort_Retention'!$A$4:$A$222=$A15)*('19_Cohort_Retention'!$B$4:$B$222=G$4))=0,"",SUMPRODUCT(('19_Cohort_Retention'!$A$4:$A$222=$A15)*('19_Cohort_Retention'!$B$4:$B$222=G$4)*'19_Cohort_Retention'!$D$4:$D$222)) -> 0.17 | H15: =IF(SUMPRODUCT(('19_Cohort_Retention'!$A$4:$A$222=$A15)*('19_Cohort_Retention'!$B$4:$B$222=H$4))=0,"",SUMPRODUCT(('19_Cohort_Retention'!$A$4:$A$222=$A15)*('19_Cohort_Retention'!$B$4:$B$222=H$4)*'19_Cohort_Retention'!$D$4:$D$222)) -> 0.18 | I15: =IF(SUMPRODUCT(('19_Cohort_Retention'!$A$4:$A$222=$A15)*('19_Cohort_Retention'!$B$4:$B$222=I$4))=0,"",SUMPRODUCT(('19_Cohort_Retention'!$A$4:$A$222=$A15)*('19_Cohort_Retention'!$B$4:$B$222=I$4)*'19_Cohort_Retention'!$D$4:$D$222)) -> 0.11 | J15: =IF(SUMPRODUCT(('19_Cohort_Retention'!$A$4:$A$222=$A15)*('19_Cohort_Retention'!$B$4:$B$222=J$4))=0,"",SUMPRODUCT(('19_Cohort_Retention'!$A$4:$A$222=$A15)*('19_Cohort_Retention'!$B$4:$B$222=J$4)*'19_Cohort_Retention'!$D$4:$D$222)) -> 0.18 | ... O15: =IF(SUMPRODUCT(('19_Cohort_Retention'!$A$4:$A$222=$A15)*('19_Cohort_Retention'!$B$4:$B$222=O$4))=0,"",SUMPRODUCT(('19_Cohort_Retention'!$A$4:$A$222=$A15)*('19_Cohort_Retention'!$B$4:$B$222=O$4)*'19_Cohort_Retention'!$D$4:$D$222))
A16: 2017-12 | B16: =SUMPRODUCT(('19_Cohort_Retention'!$A$4:$A$222=$A16)*('19_Cohort_Retention'!$B$4:$B$222=0)*'19_Cohort_Retention'!$C$4:$C$222) -> 5338 | C16: =IF(SUMPRODUCT(('19_Cohort_Retention'!$A$4:$A$222=$A16)*('19_Cohort_Retention'!$B$4:$B$222=C$4))=0,"",SUMPRODUCT(('19_Cohort_Retention'!$A$4:$A$222=$A16)*('19_Cohort_Retention'!$B$4:$B$222=C$4)*'19_Cohort_Retention'!$D$4:$D$222)) -> 100 | D16: =IF(SUMPRODUCT(('19_Cohort_Retention'!$A$4:$A$222=$A16)*('19_Cohort_Retention'!$B$4:$B$222=D$4))=0,"",SUMPRODUCT(('19_Cohort_Retention'!$A$4:$A$222=$A16)*('19_Cohort_Retention'!$B$4:$B$222=D$4)*'19_Cohort_Retention'!$D$4:$D$222)) -> 0.21 | E16: =IF(SUMPRODUCT(('19_Cohort_Retention'!$A$4:$A$222=$A16)*('19_Cohort_Retention'!$B$4:$B$222=E$4))=0,"",SUMPRODUCT(('19_Cohort_Retention'!$A$4:$A$222=$A16)*('19_Cohort_Retention'!$B$4:$B$222=E$4)*'19_Cohort_Retention'!$D$4:$D$222)) -> 0.28 | F16: =IF(SUMPRODUCT(('19_Cohort_Retention'!$A$4:$A$222=$A16)*('19_Cohort_Retention'!$B$4:$B$222=F$4))=0,"",SUMPRODUCT(('19_Cohort_Retention'!$A$4:$A$222=$A16)*('19_Cohort_Retention'!$B$4:$B$222=F$4)*'19_Cohort_Retention'!$D$4:$D$222)) -> 0.34 | G16: =IF(SUMPRODUCT(('19_Cohort_Retention'!$A$4:$A$222=$A16)*('19_Cohort_Retention'!$B$4:$B$222=G$4))=0,"",SUMPRODUCT(('19_Cohort_Retention'!$A$4:$A$222=$A16)*('19_Cohort_Retention'!$B$4:$B$222=G$4)*'19_Cohort_Retention'!$D$4:$D$222)) -> 0.26 | H16: =IF(SUMPRODUCT(('19_Cohort_Retention'!$A$4:$A$222=$A16)*('19_Cohort_Retention'!$B$4:$B$222=H$4))=0,"",SUMPRODUCT(('19_Cohort_Retention'!$A$4:$A$222=$A16)*('19_Cohort_Retention'!$B$4:$B$222=H$4)*'19_Cohort_Retention'!$D$4:$D$222)) -> 0.21 | I16: =IF(SUMPRODUCT(('19_Cohort_Retention'!$A$4:$A$222=$A16)*('19_Cohort_Retention'!$B$4:$B$222=I$4))=0,"",SUMPRODUCT(('19_Cohort_Retention'!$A$4:$A$222=$A16)*('19_Cohort_Retention'!$B$4:$B$222=I$4)*'19_Cohort_Retention'!$D$4:$D$222)) -> 0.17 | J16: =IF(SUMPRODUCT(('19_Cohort_Retention'!$A$4:$A$222=$A16)*('19_Cohort_Retention'!$B$4:$B$222=J$4))=0,"",SUMPRODUCT(('19_Cohort_Retention'!$A$4:$A$222=$A16)*('19_Cohort_Retention'!$B$4:$B$222=J$4)*'19_Cohort_Retention'!$D$4:$D$222)) -> 0.02 | ... O16: =IF(SUMPRODUCT(('19_Cohort_Retention'!$A$4:$A$222=$A16)*('19_Cohort_Retention'!$B$4:$B$222=O$4))=0,"",SUMPRODUCT(('19_Cohort_Retention'!$A$4:$A$222=$A16)*('19_Cohort_Retention'!$B$4:$B$222=O$4)*'19_Cohort_Retention'!$D$4:$D$222))
... A24: 2018-08 | B24: =SUMPRODUCT(('19_Cohort_Retention'!$A$4:$A$222=$A24)*('19_Cohort_Retention'!$B$4:$B$222=0)*'19_Cohort_Retention'!$C$4:$C$222) -> 6144 | C24: =IF(SUMPRODUCT(('19_Cohort_Retention'!$A$4:$A$222=$A24)*('19_Cohort_Retention'!$B$4:$B$222=C$4))=0,"",SUMPRODUCT(('19_Cohort_Retention'!$A$4:$A$222=$A24)*('19_Cohort_Retention'!$B$4:$B$222=C$4)*'19_Cohort_Retention'!$D$4:$D$222)) -> 100 | D24: =IF(SUMPRODUCT(('19_Cohort_Retention'!$A$4:$A$222=$A24)*('19_Cohort_Retention'!$B$4:$B$222=D$4))=0,"",SUMPRODUCT(('19_Cohort_Retention'!$A$4:$A$222=$A24)*('19_Cohort_Retention'!$B$4:$B$222=D$4)*'19_Cohort_Retention'!$D$4:$D$222)) | E24: =IF(SUMPRODUCT(('19_Cohort_Retention'!$A$4:$A$222=$A24)*('19_Cohort_Retention'!$B$4:$B$222=E$4))=0,"",SUMPRODUCT(('19_Cohort_Retention'!$A$4:$A$222=$A24)*('19_Cohort_Retention'!$B$4:$B$222=E$4)*'19_Cohort_Retention'!$D$4:$D$222)) | F24: =IF(SUMPRODUCT(('19_Cohort_Retention'!$A$4:$A$222=$A24)*('19_Cohort_Retention'!$B$4:$B$222=F$4))=0,"",SUMPRODUCT(('19_Cohort_Retention'!$A$4:$A$222=$A24)*('19_Cohort_Retention'!$B$4:$B$222=F$4)*'19_Cohort_Retention'!$D$4:$D$222)) | G24: =IF(SUMPRODUCT(('19_Cohort_Retention'!$A$4:$A$222=$A24)*('19_Cohort_Retention'!$B$4:$B$222=G$4))=0,"",SUMPRODUCT(('19_Cohort_Retention'!$A$4:$A$222=$A24)*('19_Cohort_Retention'!$B$4:$B$222=G$4)*'19_Cohort_Retention'!$D$4:$D$222)) | H24: =IF(SUMPRODUCT(('19_Cohort_Retention'!$A$4:$A$222=$A24)*('19_Cohort_Retention'!$B$4:$B$222=H$4))=0,"",SUMPRODUCT(('19_Cohort_Retention'!$A$4:$A$222=$A24)*('19_Cohort_Retention'!$B$4:$B$222=H$4)*'19_Cohort_Retention'!$D$4:$D$222)) | I24: =IF(SUMPRODUCT(('19_Cohort_Retention'!$A$4:$A$222=$A24)*('19_Cohort_Retention'!$B$4:$B$222=I$4))=0,"",SUMPRODUCT(('19_Cohort_Retention'!$A$4:$A$222=$A24)*('19_Cohort_Retention'!$B$4:$B$222=I$4)*'19_Cohort_Retention'!$D$4:$D$222)) | J24: =IF(SUMPRODUCT(('19_Cohort_Retention'!$A$4:$A$222=$A24)*('19_Cohort_Retention'!$B$4:$B$222=J$4))=0,"",SUMPRODUCT(('19_Cohort_Retention'!$A$4:$A$222=$A24)*('19_Cohort_Retention'!$B$4:$B$222=J$4)*'19_Cohort_Retention'!$D$4:$D$222)) | ... O24: =IF(SUMPRODUCT(('19_Cohort_Retention'!$A$4:$A$222=$A24)*('19_Cohort_Retention'!$B$4:$B$222=O$4))=0,"",SUMPRODUCT(('19_Cohort_Retention'!$A$4:$A$222=$A24)*('19_Cohort_Retention'!$B$4:$B$222=O$4)*'19_Cohort_Retention'!$D$4:$D$222))
A26: Reading the chart: retention after the first month is below 1% for almost every cohort, so almost no customers come back. This is the single biggest growth opportunity.

Sheet About
A1: About this workbook
A3: Project | B3: Olist E-commerce sales and delivery analysis (MySQL + Excel)
A4: Dataset | B4: Brazilian E-Commerce Public Dataset by Olist (Kaggle). 99,441 orders, Sep 2016 - Oct 2018.
A5: Currency | B5: Brazilian Real (R$).
A6: Revenue | B6: Sum of item prices in delivered orders. Freight is excluded.
A7: Late delivery | B7: Order delivered on a date after the estimated delivery date.
A8: Customers | B8: Counted by customer_unique_id (a customer_id is created per order).
A9: Review score | B9: Average of all reviews attached to an order.
A10: Data limits | B10: Sep-Dec 2016 and Sep-Oct 2018 contain very few orders, so charts focus on Jan 2017 - Aug 2018.
A11: Sheets | B11: Dashboard, Cohort_Heatmap, then 01 to 20 = one sheet per SQL query result, in the same order as 04_analysis_queries.sql.
A12: Charts | B12: All charts and KPI cards read from the numbered sheets, so they update if you paste new query results in the same layout.

Sheet 01_KPI_Summary
A1: Headline KPIs for delivered orders
A2: Source: MySQL query result (01_KPI_Summary). Amounts in Brazilian Real (R$).
A3: delivered_orders | B3: unique_customers | C3: total_revenue | D3: total_freight | E3: avg_order_value | F3: avg_delivery_days | G3: avg_estimated_days | H3: late_delivery_pct | I3: avg_review_score
A4: 96478 | B4: 93358 | C4: 13221498 | D4: 2198275.6 | E4: 137.04 | F4: 12.5 | G4: 24.4 | H4: 6.77 | I4: 4.16

Sheet 02_Order_Status
A1: Orders by status (all 99,441 orders)
A2: Source: MySQL query result (02_Order_Status). Amounts in Brazilian Real (R$).
A3: order_status | B3: orders | C3: pct_of_orders
A4: delivered | B4: 96478 | C4: 97.02
A5: shipped | B5: 1107 | C5: 1.11
A6: canceled | B6: 625 | C6: 0.63
A7: unavailable | B7: 609 | C7: 0.61
A8: invoiced | B8: 314 | C8: 0.32
A9: processing | B9: 301 | C9: 0.3
A10: created | B10: 5 | C10: 0.01
A11: approved | B11: 2 | C11: 0

Sheet 03_Monthly_Trend
A1: Monthly orders, revenue and month-over-month growth
A2: Source: MySQL query result (03_Monthly_Trend). Amounts in Brazilian Real (R$).
A3: purchase_month | B3: orders | C3: revenue | D3: avg_order_value | E3: revenue_mom_growth_pct | F3: cumulative_revenue
A4: 2016-09 | B4: 1 | C4: 134.97 | D4: 134.97 | F4: 134.97
A5: 2016-10 | B5: 265 | C5: 40325.11 | D5: 152.17 | E5: 29777.09 | F5: 40460.08
A6: 2016-12 | B6: 1 | C6: 10.9 | D6: 10.9 | E6: -99.97 | F6: 40470.98
A7: 2017-01 | B7: 750 | C7: 111798.36 | D7: 149.06 | E7: 1025573 | F7: 152269.34
A8: 2017-02 | B8: 1653 | C8: 234223.4 | D8: 141.7 | E8: 109.51 | F8: 386492.74
A9: 2017-03 | B9: 2546 | C9: 359198.85 | D9: 141.08 | E9: 53.36 | F9: 745691.59
A10: 2017-04 | B10: 2303 | C10: 340669.68 | D10: 147.92 | E10: -5.16 | F10: 1086361.3
A11: 2017-05 | B11: 3546 | C11: 489338.25 | D11: 138 | E11: 43.64 | F11: 1575699.5
A12: 2017-06 | B12: 3135 | C12: 421923.37 | D12: 134.58 | E12: -13.78 | F12: 1997622.9
A13: 2017-07 | B13: 3872 | C13: 481604.52 | D13: 124.38 | E13: 14.15 | F13: 2479227.4
A14: 2017-08 | B14: 4193 | C14: 554699.7 | D14: 132.29 | E14: 15.18 | F14: 3033927.1
A15: 2017-09 | B15: 4150 | C15: 607399.67 | D15: 146.36 | E15: 9.5 | F15: 3641326.8
A16: 2017-10 | B16: 4478 | C16: 648247.65 | D16: 144.76 | E16: 6.73 | F16: 4289574.4
... A26: 2018-08 | B26: 6351 | C26: 838576.64 | D26: 132.04 | E26: -3.38 | F26: 13221498

Sheet 04_Yearly_Summary
A1: Yearly summary
A2: Source: MySQL query result (04_Yearly_Summary). Amounts in Brazilian Real (R$).
A3: purchase_year | B3: orders | C3: revenue | D3: avg_order_value | E3: unique_customers
A4: 2016 | B4: 267 | C4: 40470.98 | D4: 151.58 | E4: 264
A5: 2017 | B5: 43428 | C5: 5962902 | D5: 137.31 | E5: 42136
A6: 2018 | B6: 52783 | C6: 7218125.1 | D6: 136.75 | E6: 51612

Sheet 05_Weekday_Pattern
A1: Orders by weekday
A2: Source: MySQL query result (05_Weekday_Pattern). Amounts in Brazilian Real (R$).
A3: weekday_num | B3: weekday_name | C3: orders | D3: revenue
A4: 0 | B4: Monday | C4: 15701 | D4: 2168905.6
A5: 1 | B5: Tuesday | C5: 15503 | D5: 2122264.5
A6: 2 | B6: Wednesday | C6: 15076 | D6: 2051533.7
A7: 3 | B7: Thursday | C7: 14323 | D7: 1958600.5
A8: 4 | B8: Friday | C8: 13685 | D8: 1910496.1
A9: 5 | B9: Saturday | C9: 10555 | D9: 1464049.6
A10: 6 | B10: Sunday | C10: 11635 | D10: 1545648.1

Sheet 06_Hourly_Pattern
A1: Orders by hour of day
A2: Source: MySQL query result (06_Hourly_Pattern). Amounts in Brazilian Real (R$).
A3: purchase_hour | B3: orders | C3: revenue
A4: 0 | B4: 2321 | C4: 307166.35
A5: 1 | B5: 1133 | C5: 147608.07
A6: 2 | B6: 496 | C6: 54028.76
A7: 3 | B7: 259 | C7: 32100.68
A8: 4 | B8: 203 | C8: 24191.61
A9: 5 | B9: 182 | C9: 21905.22
A10: 6 | B10: 478 | C10: 53772.91
A11: 7 | B11: 1199 | C11: 147781.69
A12: 8 | B12: 2907 | C12: 386356.06
A13: 9 | B13: 4647 | C13: 666581.16
A14: 10 | B14: 5978 | C14: 813492.67
A15: 11 | B15: 6385 | C15: 852420.68
... A27: 23 | B27: 4015 | C27: 514794.86

Sheet 07_Category_Performance
A1: Revenue by product category
A2: Source: MySQL query result (07_Category_Performance). Amounts in Brazilian Real (R$).
A3: revenue_rank | B3: category | C3: orders | D3: units_sold | E3: revenue | F3: revenue_share_pct | G3: avg_item_price | H3: avg_review_score
A4: 1 | B4: health_beauty | C4: 8647 | D4: 9465 | E4: 1233131.7 | F4: 9.33 | G4: 130.28 | H4: 4.19
A5: 2 | B5: watches_gifts | C5: 5495 | D5: 5859 | E5: 1166177 | F5: 8.82 | G5: 199.04 | H5: 4.07
A6: 3 | B6: bed_bath_table | C6: 9272 | D6: 10953 | E6: 1023434.8 | F6: 7.74 | G6: 93.44 | H6: 3.92
A7: 4 | B7: sports_leisure | C7: 7530 | D7: 8431 | E7: 954852.55 | F7: 7.22 | G7: 113.25 | H7: 4.17
A8: 5 | B8: computers_accessories | C8: 6530 | D8: 7644 | E8: 888724.61 | F8: 6.72 | G8: 116.26 | H8: 3.99
A9: 6 | B9: furniture_decor | C9: 6307 | D9: 8160 | E9: 711927.69 | F9: 5.38 | G9: 87.25 | H9: 3.95
A10: 7 | B10: housewares | C10: 5743 | D10: 6795 | E10: 615628.69 | F10: 4.66 | G10: 90.6 | H10: 4.11
A11: 8 | B11: cool_stuff | C11: 3559 | D11: 3718 | E11: 610204.1 | F11: 4.62 | G11: 164.12 | H11: 4.19
A12: 9 | B12: auto | C12: 3810 | D12: 4140 | E12: 578966.65 | F12: 4.38 | G12: 139.85 | H12: 4.12
A13: 10 | B13: toys | C13: 3804 | D13: 4030 | E13: 471286.48 | F13: 3.56 | G13: 116.94 | H13: 4.21
A14: 11 | B14: garden_tools | C14: 3448 | D14: 4268 | E14: 470495.28 | F14: 3.56 | G14: 110.24 | H14: 4.08
A15: 12 | B15: baby | C15: 2809 | D15: 2982 | E15: 400421.84 | F15: 3.03 | G15: 134.28 | H15: 4.08
... A77: 74 | B77: security_and_services | C77: 2 | D77: 2 | E77: 283.29 | F77: 0 | G77: 141.65 | H77: 2.5

Sheet 08_Pareto_ABC
A1: Pareto (80/20) and ABC class by category
A2: Source: MySQL query result (08_Pareto_ABC). Amounts in Brazilian Real (R$).
A3: category | B3: revenue | C3: share_pct | D3: cumulative_pct | E3: abc_class
A4: health_beauty | B4: 1233131.7 | C4: 9.33 | D4: 9.33 | E4: A
A5: watches_gifts | B5: 1166177 | C5: 8.82 | D5: 18.15 | E5: A
A6: bed_bath_table | B6: 1023434.8 | C6: 7.74 | D6: 25.89 | E6: A
A7: sports_leisure | B7: 954852.55 | C7: 7.22 | D7: 33.11 | E7: A
A8: computers_accessories | B8: 888724.61 | C8: 6.72 | D8: 39.83 | E8: A
A9: furniture_decor | B9: 711927.69 | C9: 5.38 | D9: 45.22 | E9: A
A10: housewares | B10: 615628.69 | C10: 4.66 | D10: 49.87 | E10: A
A11: cool_stuff | B11: 610204.1 | C11: 4.62 | D11: 54.49 | E11: A
A12: auto | B12: 578966.65 | C12: 4.38 | D12: 58.87 | E12: A
A13: toys | B13: 471286.48 | C13: 3.56 | D13: 62.43 | E13: A
A14: garden_tools | B14: 470495.28 | C14: 3.56 | D14: 65.99 | E14: A
A15: baby | B15: 400421.84 | C15: 3.03 | D15: 69.02 | E15: A
... A77: security_and_services | B77: 283.29 | C77: 0 | D77: 100 | E77: C

Sheet 09_State_Performance
A1: Performance by customer state | K1: Late % ranking (states with 500+ orders)
A2: Source: MySQL query result (09_State_Performance). Amounts in Brazilian Real (R$).
A3: customer_state | B3: orders | C3: customers | D3: revenue | E3: avg_order_value | F3: freight_pct_of_revenue | G3: avg_delivery_days | H3: late_delivery_pct | I3: avg_review_score | K3: state | L3: late_delivery_pct
A4: SP | B4: 40501 | C4: 39156 | D4: 5067633.2 | E4: 125.12 | F4: 13.85 | G4: 8.7 | H4: 4.49 | I4: 4.25 | K4: =A18 -> MA | L4: =H18 -> 17.43
A5: RJ | B5: 12350 | C5: 11917 | D5: 1759651.1 | E5: 142.48 | F5: 16.81 | G5: 15.2 | H5: 12.11 | I5: 3.97 | K5: =A15 -> CE | L5: =H15 -> 13.76
A6: MG | B6: 11354 | C6: 11001 | D6: 1552481.8 | E6: 136.73 | F6: 17.16 | G6: 11.9 | H6: 4.57 | I6: 4.19 | K6: =A10 -> BA | L6: =H10 -> 12.16
A7: RS | B7: 5345 | C7: 5168 | D7: 728897.47 | E7: 136.37 | F7: 18.19 | G7: 15.2 | H7: 6.08 | I7: 4.19 | K7: =A5 -> RJ | L7: =H5 -> 12.11
A8: PR | B8: 4923 | C8: 4769 | D8: 666063.51 | E8: 135.3 | F8: 17.36 | G8: 11.9 | H8: 4.04 | I8: 4.24 | K8: =A16 -> PA | L8: =H16 -> 11.21
A9: SC | B9: 3546 | C9: 3449 | D9: 507012.13 | E9: 142.98 | F9: 17.38 | G9: 14.9 | H9: 8.21 | I9: 4.13 | K9: =A13 -> ES | L9: =H13 -> 10.73
A10: BA | B10: 3256 | C10: 3158 | D10: 493584.14 | E10: 151.59 | F10: 19.76 | G10: 19.3 | H10: 12.16 | I10: 3.93 | K10: =A20 -> PB | L10: =H20 -> 10.44
A11: DF | B11: 2080 | C11: 2019 | D11: 296498.41 | E11: 142.55 | F11: 16.74 | G11: 12.9 | H11: 5.67 | I11: 4.13 | K11: =A19 -> MS | L11: =H19 -> 9.7
A12: GO | B12: 1957 | C12: 1895 | D12: 282836.7 | E12: 144.53 | F12: 18.16 | G12: 15.5 | H12: 6.54 | I12: 4.1 | K12: =A14 -> PE | L12: =H14 -> 9.6
A13: ES | B13: 1995 | C13: 1928 | D13: 268643.45 | E13: 134.66 | F13: 18.25 | G13: 15.7 | H13: 10.73 | I13: 4.08 | K13: =A9 -> SC | L13: =H9 -> 8.21
A14: PE | B14: 1593 | C14: 1551 | D14: 251889.49 | E14: 158.12 | F14: 22.66 | G14: 18.4 | H14: 9.6 | I14: 4.08
A15: CE | B15: 1279 | C15: 1258 | D15: 219757.38 | E15: 171.82 | F15: 21.24 | G15: 21.2 | H15: 13.76 | I15: 3.94
A16: PA | B16: 946 | C16: 922 | D16: 174470.59 | E16: 184.43 | F16: 21.52 | G16: 23.7 | H16: 11.21 | I16: 3.91
A17: MT | B17: 886 | C17: 856 | D17: 152191.62 | E17: 171.77 | F17: 19.08 | G17: 18 | H17: 5.98 | I17: 4.15
A18: MA | B18: 717 | C18: 700 | D18: 117009.38 | E18: 163.19 | F18: 26.32 | G18: 21.5 | H18: 17.43 | I18: 3.83
A19: MS | B19: 701 | C19: 681 | D19: 115429.97 | E19: 164.66 | F19: 16.41 | G19: 15.5 | H19: 9.7 | I19: 4.16
A20: PB | B20: 517 | C20: 504 | D20: 112586.82 | E20: 217.77 | F20: 22.43 | G20: 20.4 | H20: 10.44 | I20: 4.08
A21: PI | B21: 476 | C21: 464 | D21: 84721 | E21: 177.99 | F21: 24.15 | G21: 19.4 | H21: 13.87 | I21: 3.99
A22: RN | B22: 474 | C22: 464 | D22: 82105.66 | E22: 173.22 | F22: 22.66 | G22: 19.2 | H22: 9.28 | I22: 4.15
A23: AL | B23: 397 | C23: 387 | D23: 78855.72 | E23: 198.63 | F23: 19.42 | G23: 24.5 | H23: 21.41 | I23: 3.85
A24: SE | B24: 335 | C24: 329 | D24: 56574.19 | E24: 168.88 | F24: 24.24 | G24: 21.5 | H24: 15.22 | I24: 3.91
A25: TO | B25: 274 | C25: 267 | D25: 48402.51 | E25: 176.65 | F25: 23.98 | G25: 17.6 | H25: 9.85 | I25: 4.15
... A30: RR | B30: 41 | C30: 40 | D30: 7057.47 | E30: 172.13 | F30: 28.08 | G30: 29.3 | H30: 12.2 | I30: 3.9

Sheet 10_Payment_Types
A1: Payment method mix
A2: Source: MySQL query result (10_Payment_Types). Amounts in Brazilian Real (R$).
A3: payment_type | B3: orders | C3: total_value | D3: value_share_pct | E3: avg_payment_value
A4: credit_card | B4: 74304 | C4: 12101095 | D4: 78.46 | E4: 162.24
A5: boleto | B5: 19191 | C5: 2769932.6 | D5: 17.96 | E5: 144.33
A6: voucher | B6: 3679 | C6: 343013.19 | D6: 2.22 | E6: 62.45
A7: debit_card | B7: 1485 | C7: 208421.12 | D7: 1.35 | E7: 140.26

Sheet 11_Credit_Installments
A1: Credit card installment groups
A2: Source: MySQL query result (11_Credit_Installments). Amounts in Brazilian Real (R$).
A3: installment_group | B3: payments | C3: avg_payment_value
A4: 1 (pay in full) | B4: 24761 | C4: 95.6
A5: 2-3 | B5: 22239 | C5: 133.63
A6: 4-6 | B6: 15790 | C6: 180.48
A7: 7-10 | B7: 11467 | C7: 330.87
A8: 11+ | B8: 329 | C8: 359.4

Sheet 12_Delivery_Trend
A1: Delivery time and late % by month
A2: Source: MySQL query result (12_Delivery_Trend). Amounts in Brazilian Real (R$).
A3: purchase_month | B3: delivered_orders | C3: avg_delivery_days | D3: avg_estimated_days | E3: late_delivery_pct
A4: 2016-09 | B4: 1 | C4: 55 | D4: 19 | E4: 100
A5: 2016-10 | B5: 265 | C5: 19.6 | D5: 56.3 | E5: 0.75
A6: 2016-12 | B6: 1 | C6: 5 | D6: 27 | E6: 0
A7: 2017-01 | B7: 750 | C7: 12.8 | D7: 40.2 | E7: 2.93
A8: 2017-02 | B8: 1653 | C8: 13.3 | D8: 32.5 | E8: 2.96
A9: 2017-03 | B9: 2546 | C9: 13 | D9: 25.4 | E9: 4.56
A10: 2017-04 | B10: 2303 | C10: 15 | D10: 28 | E10: 6.56
A11: 2017-05 | B11: 3545 | C11: 11.4 | D11: 24.9 | E11: 2.99
A12: 2017-06 | B12: 3135 | C12: 12 | D12: 24.7 | E12: 3.03
A13: 2017-07 | B13: 3872 | C13: 11.5 | D13: 24 | E13: 2.79
A14: 2017-08 | B14: 4193 | C14: 11 | D14: 24.1 | E14: 2.91
A15: 2017-09 | B15: 4150 | C15: 11.7 | D15: 23.1 | E15: 4.39
... A26: 2018-08 | B26: 6351 | C26: 7.7 | D26: 15.8 | E26: 6.19

Sheet 13_Late_vs_OnTime
A1: Customer review: late vs on-time delivery
A2: Source: MySQL query result (13_Late_vs_OnTime). Amounts in Brazilian Real (R$).
A3: delivery_outcome | B3: orders | C3: avg_review_score | D3: pct_negative_reviews | E3: avg_delivery_days
A4: On time / early | B4: 89936 | C4: 4.29 | D4: 9.23 | E4: 10.9
A5: Late | B5: 6534 | C5: 2.27 | D5: 62.36 | E5: 33.9

Sheet 14_Delay_Buckets
A1: Review score by delivery delay bucket
A2: Source: MySQL query result (14_Delay_Buckets). Amounts in Brazilian Real (R$).
A3: sort_no | B3: delivery_bucket | C3: orders | D3: avg_review_score | E3: pct_negative_reviews | H3: short_label
A4: 1 | B4: 1. Very early (8+ days before estimate) | C4: 71303 | D4: 4.32 | E4: 8.94 | H4: =MID(B4,4,FIND(" (",B4&" (")-4) -> Very early
A5: 2 | B5: 2. Early (1-7 days before estimate) | C5: 17341 | D5: 4.2 | E5: 10.21 | H5: =MID(B5,4,FIND(" (",B5&" (")-4) -> Early
A6: 3 | B6: 3. On the estimated date | C6: 1292 | D6: 4.04 | E6: 12.27 | H6: =MID(B6,4,FIND(" (",B6&" (")-4) -> On the estimated date
A7: 4 | B7: 4. Late 1-3 days | C7: 1870 | D7: 3.29 | E7: 32.18 | H7: =MID(B7,4,FIND(" (",B7&" (")-4) -> Late 1-3 days
A8: 5 | B8: 5. Late 4-7 days | C8: 1802 | D8: 2.11 | E8: 67.56 | H8: =MID(B8,4,FIND(" (",B8&" (")-4) -> Late 4-7 days
A9: 6 | B9: 6. Late 8+ days | C9: 2862 | D9: 1.7 | E9: 79.18 | H9: =MID(B9,4,FIND(" (",B9&" (")-4) -> Late 8+ days

Sheet 15_Top_Sellers
A1: Top 10 sellers by revenue
A2: Source: MySQL query result (15_Top_Sellers). Amounts in Brazilian Real (R$).
A3: seller_id | B3: seller_state | C3: orders | D3: revenue | E3: avg_review_score | F3: late_item_pct
A4: 4869f7a5dfa277a7dca6462dcf3b52b2 | B4: SP | C4: 1124 | D4: 226987.93 | E4: 4.14 | F4: 10.54
A5: 53243585a1d6dc2643021fd1853d8905 | B5: BA | C5: 348 | D5: 217940.44 | E5: 4.13 | F5: 3
A6: 4a3ca9315b744ce9f8e9374361493884 | B6: SP | C6: 1772 | D6: 196882.12 | E6: 3.83 | F6: 9.7
A7: fa1c13f2614d7b5c4749cbc52fecda94 | B7: SP | C7: 578 | D7: 190917.14 | E7: 4.37 | F7: 9.15
A8: 7c67e1448b00f6e969d365cea6b010ab | B8: SP | C8: 973 | D8: 186570.05 | E8: 3.35 | F8: 8.86
A9: 7e93a43ef30c4f03f38b393420bc753a | B9: SP | C9: 319 | D9: 165981.49 | E9: 4.36 | F9: 4.66
A10: da8622b14eb17ae2831f4ac5b9dab84a | B10: SP | C10: 1311 | D10: 159816.87 | E10: 4.07 | F10: 6.4
A11: 7a67c85e85bb2ce8582c35f2203ad736 | B11: SP | C11: 1145 | D11: 139658.69 | E11: 4.27 | F11: 5.19
A12: 1025f0e2d44d7041d6cf58b6550e0bfa | B12: SP | C12: 910 | D12: 138208.56 | E12: 3.87 | F12: 6.69
A13: 955fee9216a65b617aa5c0531780ce60 | B13: SP | C13: 1261 | D13: 131836.71 | E13: 4.09 | F13: 6.45

Sheet 16_Risky_Sellers
A1: 10 lowest-rated sellers (30+ orders)
A2: Source: MySQL query result (16_Risky_Sellers). Amounts in Brazilian Real (R$).
A3: seller_id | B3: seller_state | C3: orders | D3: revenue | E3: avg_review_score | F3: late_item_pct
A4: 1ca7077d890b907f89be8c954a02686a | B4: SP | C4: 108 | D4: 12474.64 | E4: 2.27 | F4: 14.96
A5: 2eb70248d66e0e3ef83659f71b244378 | B5: SP | C5: 187 | D5: 38990.72 | E5: 2.81 | F5: 11.68
A6: 972d0f9cf61b499a4812cf0bfa3ad3c4 | B6: SC | C6: 81 | D6: 7910.42 | E6: 2.96 | F6: 11.63
A7: a49928bcdf77c55c6d6e05e09a9b4ca5 | B7: SP | C7: 96 | D7: 8646.9 | E7: 2.97 | F7: 21.15
A8: 8e6d7754bc7e0f22c96d255ebda59eba | B8: SP | C8: 84 | D8: 14107.38 | E8: 2.99 | F8: 10.08
A9: 2a1348e9addc1af5aaa619b1a3679d6b | B9: MG | C9: 48 | D9: 2697.4 | E9: 3.04 | F9: 29.41
A10: 602044f2c16190c2c6e45eb35c2e21cb | B10: SP | C10: 48 | D10: 3559.17 | E10: 3.04 | F10: 20
A11: bbad7e518d7af88a0897397ffdca1979 | B11: SP | C11: 68 | D11: 4426.32 | E11: 3.05 | F11: 22.62
A12: 54965bbe3e4f07ae045b90b0b8541f52 | B12: PR | C12: 73 | D12: 10351.7 | E12: 3.07 | F12: 32.1
A13: 5058e8c1e82653974541e83690655b4a | B13: SP | C13: 62 | D13: 9812.83 | E13: 3.08 | F13: 10.39

Sheet 17_Repeat_Customers
A1: Repeat customer rate
A2: Source: MySQL query result (17_Repeat_Customers). Amounts in Brazilian Real (R$).
A3: total_customers | B3: repeat_customers | C3: repeat_rate_pct
A4: 93358 | B4: 2801 | C4: 3

Sheet 18_Order_Frequency
A1: Customers by number of orders
A2: Source: MySQL query result (18_Order_Frequency). Amounts in Brazilian Real (R$).
A3: orders_placed | B3: customers | C3: pct_of_customers | D3: revenue
A4: 1 | B4: 90557 | C4: 97 | D4: 12493089
A5: 2 | B5: 2573 | C5: 2.76 | D5: 631274.9
A6: 3 | B6: 181 | C6: 0.19 | D6: 65974.42
A7: 4+ | B7: 47 | C7: 0.05 | D7: 31159.43

Sheet 19_Cohort_Retention
A1: Cohort retention (customers returning after first purchase month)
A2: Source: MySQL query result (19_Cohort_Retention). Amounts in Brazilian Real (R$).
A3: cohort_month | B3: month_index | C3: active_customers | D3: retention_pct
A4: 2016-09 | B4: 0 | C4: 1 | D4: 100
A5: 2016-10 | B5: 0 | C5: 262 | D5: 100
A6: 2016-10 | B6: 6 | C6: 1 | D6: 0.38
A7: 2016-10 | B7: 9 | C7: 1 | D7: 0.38
A8: 2016-10 | B8: 11 | C8: 1 | D8: 0.38
A9: 2016-10 | B9: 13 | C9: 1 | D9: 0.38
A10: 2016-10 | B10: 15 | C10: 1 | D10: 0.38
A11: 2016-10 | B11: 17 | C11: 1 | D11: 0.38
A12: 2016-10 | B12: 19 | C12: 2 | D12: 0.76
A13: 2016-10 | B13: 20 | C13: 2 | D13: 0.76
A14: 2016-12 | B14: 0 | C14: 1 | D14: 100
A15: 2016-12 | B15: 1 | C15: 1 | D15: 100
... A222: 2018-08 | B222: 0 | C222: 6144 | D222: 100

Sheet 20_RFM_Segments
A1: RFM customer segments
A2: Source: MySQL query result (20_RFM_Segments). Amounts in Brazilian Real (R$).
A3: segment | B3: customers | C3: pct_of_customers | D3: avg_recency_days | E3: avg_orders | F3: avg_spend | G3: total_revenue | H3: pct_of_revenue | J3: short_segment
A4: Champions (recent, high spend) | B4: 15362 | C4: 16.45 | D4: 91 | E4: 1.07 | F4: 271.26 | G4: 4167112.3 | H4: 31.52 | J4: =LEFT(A4,FIND(" (",A4&" (")-1) -> Champions
A5: At risk big spenders | B5: 14563 | C5: 15.6 | D5: 394 | E5: 1.05 | F5: 278.08 | G5: 4049679.3 | H5: 30.63 | J5: =LEFT(A5,FIND(" (",A5&" (")-1) -> At risk big spenders
A6: Needs attention | B6: 25461 | C6: 27.27 | D6: 269 | E6: 1.01 | F6: 117.99 | G6: 3004074.6 | H6: 22.72 | J6: =LEFT(A6,FIND(" (",A6&" (")-1) -> Needs attention
A7: Promising (recent, lower spend) | B7: 21710 | C7: 23.25 | D7: 89 | E7: 1 | F7: 55.65 | G7: 1208205.8 | H7: 9.14 | J7: =LEFT(A7,FIND(" (",A7&" (")-1) -> Promising
A8: Lost / low value | B8: 15385 | C8: 16.48 | D8: 396 | E8: 1.01 | F8: 40.11 | G8: 617074.49 | H8: 4.67 | J8: =LEFT(A8,FIND(" (",A8&" (")-1) -> Lost / low value
A9: Loyal repeat buyers | B9: 877 | C9: 0.94 | D9: 177 | E9: 2.07 | F9: 199.94 | G9: 175351.7 | H9: 1.33 | J9: =LEFT(A9,FIND(" (",A9&" (")-1) -> Loyal repeat buyers
